MANIFEST.in
README.txt
setup.py
docs/HISTORY.txt
docs/LICENSE.txt
src/silva/__init__.py
src/silva.app.forest.egg-info/PKG-INFO
src/silva.app.forest.egg-info/SOURCES.txt
src/silva.app.forest.egg-info/dependency_links.txt
src/silva.app.forest.egg-info/namespace_packages.txt
src/silva.app.forest.egg-info/not-zip-safe
src/silva.app.forest.egg-info/requires.txt
src/silva.app.forest.egg-info/top_level.txt
src/silva/app/__init__.py
src/silva/app/forest/__init__.py
src/silva/app/forest/absoluteurl.py
src/silva/app/forest/configure.zcml
src/silva/app/forest/events.py
src/silva/app/forest/ftesting.zcml
src/silva/app/forest/interfaces.py
src/silva/app/forest/service.png
src/silva/app/forest/service.py
src/silva/app/forest/site.py
src/silva/app/forest/testing.py
src/silva/app/forest/utils.py
src/silva/app/forest/virtualhosting.py
src/silva/app/forest/tests/__init__.py
src/silva/app/forest/tests/test_service.py
src/silva/app/forest/tests/test_utils.py
src/silva/app/forest/tests/test_virtualhosting.py
src/silva/app/forest/tests/test_virtualhosting_breadcrumbs.py
src/silva/app/forest/tests/test_virtualhosting_site.py
src/silva/app/forest/tests/test_virtualhosting_skin.py
src/silva/app/forest/tests/test_virtualhosting_url.py
src/silva/app/forest/tests/data/duplicate_hosts.csv
src/silva/app/forest/tests/data/invalid_hosts.csv
src/silva/app/forest/tests/data/valid_hosts.csv