Metadata-Version: 1.1
Name: silva.app.forest
Version: 3.0.1
Summary: Advanced virtual hosting for Silva CMS
Home-page: https://github.com/silvacms/silva.app.forest
Author: Infrae
Author-email: info@infrae.com
License: BSD
Keywords: silva advanced virtual hosting rewrite rules
Platform: UNKNOWN
Classifier: Framework :: Zope2
Classifier: License :: OSI Approved :: BSD License
Classifier: Programming Language :: Python
Classifier: Topic :: Software Development :: Libraries :: Python Modules
